<?xml version="1.0" encoding="utf-8" ?>
<dwsync>
<file name="bg.js" server="chrislavigne.com/d7.chrislavigne.com/" local="129791658020000000" remote="129885006600000000" />
<file name="cs.js" server="chrislavigne.com/d7.chrislavigne.com/" local="129791658020000000" remote="129885006600000000" />
<file name="cy.js" server="chrislavigne.com/d7.chrislavigne.com/" local="129791658020000000" remote="129885006600000000" />
<file name="da.js" server="chrislavigne.com/d7.chrislavigne.com/" local="129791658020000000" remote="129885006600000000" />
<file name="de.js" server="chrislavigne.com/d7.chrislavigne.com/" local="129791658020000000" remote="129885006600000000" />
<file name="el.js" server="chrislavigne.com/d7.chrislavigne.com/" local="129791658020000000" remote="129885006600000000" />
<file name="en.js" server="chrislavigne.com/d7.chrislavigne.com/" local="129791658020000000" remote="129885006600000000" />
<file name="eo.js" server="chrislavigne.com/d7.chrislavigne.com/" local="129791658020000000" remote="129885006600000000" />
<file name="et.js" server="chrislavigne.com/d7.chrislavigne.com/" local="129791658020000000" remote="129885006600000000" />
<file name="fa.js" server="chrislavigne.com/d7.chrislavigne.com/" local="129791658020000000" remote="129885006600000000" />
<file name="fi.js" server="chrislavigne.com/d7.chrislavigne.com/" local="129791658020000000" remote="129885006600000000" />
<file name="fr.js" server="chrislavigne.com/d7.chrislavigne.com/" local="129791658020000000" remote="129885006600000000" />
<file name="he.js" server="chrislavigne.com/d7.chrislavigne.com/" local="129791658020000000" remote="129885006600000000" />
<file name="hr.js" server="chrislavigne.com/d7.chrislavigne.com/" local="129791658020000000" remote="129885006600000000" />
<file name="it.js" server="chrislavigne.com/d7.chrislavigne.com/" local="129791658020000000" remote="129885006600000000" />
<file name="mk.js" server="chrislavigne.com/d7.chrislavigne.com/" local="129791658020000000" remote="129885006600000000" />
<file name="nb.js" server="chrislavigne.com/d7.chrislavigne.com/" local="129791658020000000" remote="129885006600000000" />
<file name="nl.js" server="chrislavigne.com/d7.chrislavigne.com/" local="129791658020000000" remote="129885006600000000" />
<file name="no.js" server="chrislavigne.com/d7.chrislavigne.com/" local="129791658020000000" remote="129885006600000000" />
<file name="pl.js" server="chrislavigne.com/d7.chrislavigne.com/" local="129791658020000000" remote="129885006600000000" />
<file name="tr.js" server="chrislavigne.com/d7.chrislavigne.com/" local="129791658020000000" remote="129885006600000000" />
<file name="ug.js" server="chrislavigne.com/d7.chrislavigne.com/" local="129791658020000000" remote="129885006600000000" />
<file name="uk.js" server="chrislavigne.com/d7.chrislavigne.com/" local="129791658020000000" remote="129885006600000000" />
<file name="vi.js" server="chrislavigne.com/d7.chrislavigne.com/" local="129791658020000000" remote="129885006600000000" />
<file name="zh-cn.js" server="chrislavigne.com/d7.chrislavigne.com/" local="129791658020000000" remote="129885006600000000" />
<file name="_translationstatus.txt" server="chrislavigne.com/d7.chrislavigne.com/" local="129791658020000000" remote="129885006600000000" />
</dwsync>